webplatform_cli/__init__.py
webplatform_cli/cli.py
webplatform_cli/commands_parser.py
webplatform_cli/handler.py
webplatform_cli/webplatform-cli
webplatform_cli/containers/__init__.py
webplatform_cli/containers/main.py
webplatform_cli/dependencies/__init__.py
webplatform_cli/dependencies/docopt.py
webplatform_cli/lib/__init__.py
webplatform_cli/lib/config.py
webplatform_cli/lib/db.py
webplatform_cli/lib/modules.py
webplatform_cli/lib/sessions.py
webplatform_cli/tasks/__init__.py
webplatform_cli/tasks/build.py
webplatform_cli-1.0.24.data/scripts/webplatform-cli
webplatform_cli-1.0.24.dist-info/METADATA
webplatform_cli-1.0.24.dist-info/WHEEL
webplatform_cli-1.0.24.dist-info/top_level.txt
webplatform_cli-1.0.24.dist-info/RECORD
