Metadata-Version: 2.1
Name: webplatform-cli
Version: 1.0.24
Summary: CLI used for a webplatform
Home-page: https://github.com/lost-osiris/webplatform-cli
Author: Matthew Owens
Author-email: mowens@redhat.com
License: MIT
Platform: UNKNOWN
Classifier: Programming Language :: Python :: 3
Classifier: License :: OSI Approved :: MIT License
Classifier: Operating System :: OS Independent
Requires-Dist: docker
Requires-Dist: pymongo
